README.rst
setup.py
pypexels/__init__.py
pypexels/pypexels.py
pypexels.egg-info/PKG-INFO
pypexels.egg-info/SOURCES.txt
pypexels.egg-info/dependency_links.txt
pypexels.egg-info/requires.txt
pypexels.egg-info/top_level.txt
pypexels/src/__init__.py
pypexels/src/curated.py
pypexels/src/errors.py
pypexels/src/liblogging.py
pypexels/src/models.py
pypexels/src/pexelspage.py
pypexels/src/popular.py
pypexels/src/random_.py
pypexels/src/rest.py
pypexels/src/search.py
pypexels/src/settings.py