Metadata-Version: 1.2
Name: pypexels
Version: 1.0.0b4
Summary: A Python wrapper for the Pexels.com REST API
Home-page: https://github.com/salvoventura/pypexels
Author: salvatore ventura
Author-email: salvoventura@gmail.com
License: MIT
Keywords: pexels,rest,api,python,wrapper,development,pexels.com,photography
Platform: UNKNOWN
Classifier: Development Status :: 4 - Beta
Classifier: Intended Audience :: Developers
Classifier: License :: OSI Approved :: MIT License
Classifier: Programming Language :: Python :: 2.7
Classifier: Programming Language :: Python :: 3.5
Classifier: Programming Language :: Python :: 3.6
Requires-Python: >=2.7
